pokedatabase_sdk/__init__.py
pokedatabase_sdk/pokedatabase_sdk.py
pokedatabase_SDK-0.0.1.dist-info/LICENSE.txt
pokedatabase_SDK-0.0.1.dist-info/METADATA
pokedatabase_SDK-0.0.1.dist-info/WHEEL
pokedatabase_SDK-0.0.1.dist-info/top_level.txt
pokedatabase_SDK-0.0.1.dist-info/RECORD
