Metadata-Version: 2.1
Name: pokedatabase-SDK
Version: 0.0.1
Summary: Pokemon information SDK
Home-page: https://github.com/AlonsoMartinToledano/pokedatabase_sdk
Author: Alonso Martin-Toledano
Author-email: alonsomtgm@gmail.com
License: MIT
Keywords: pokemon,APIRest,SDK
Platform: UNKNOWN
Classifier: Development Status :: 5 - Production/Stable
Classifier: Intended Audience :: Education
Classifier: Operating System :: Microsoft :: Windows :: Windows 10
Classifier: License :: OSI Approved :: MIT License
Classifier: Programming Language :: Python :: 3
License-File: LICENSE.txt
Requires-Dist: requests
